pavio/__init__.py
pavio/cli.py
pavio/command/__init__.py
pavio/command/configs.py
pavio/command/environments.py
pavio/exception/__init__.py
pavio/model/__init__.py
pavio/model/environment.py
pavio/module/__init__.py
pavio/module/config.py
pavio/module/database.py
pavio/module/file_system.py
pavio/module/logger.py
pavio/module/output.py
pavio-0.1.0.dist-info/LICENSE.txt
pavio-0.1.0.dist-info/METADATA
pavio-0.1.0.dist-info/WHEEL
pavio-0.1.0.dist-info/entry_points.txt
pavio-0.1.0.dist-info/top_level.txt
pavio-0.1.0.dist-info/RECORD
